evaluate_attacks/__init__.py
evaluate_attacks/attack_eval.py
evaluate_attacks-0.1.1.dist-info/METADATA
evaluate_attacks-0.1.1.dist-info/WHEEL
evaluate_attacks-0.1.1.dist-info/top_level.txt
evaluate_attacks-0.1.1.dist-info/RECORD
