Metadata-Version: 2.1
Name: evaluate-attacks
Version: 0.1.1
Summary: A package for evaluating adversarial attacks on deep learning models
Home-page: https://github.com/Cyberus-MLSec/eval_adv_attack
Author: Sahbaaz Ansari
Author-email: mlsecadversarialattack@gmail.com
Requires-Dist: torch
Requires-Dist: torchattacks
Requires-Dist: matplotlib
Requires-Dist: numpy
